pyshorteners/__init__.py
pyshorteners/base.py
pyshorteners/exceptions.py
pyshorteners/shorteners/__init__.py
pyshorteners/shorteners/adfly.py
pyshorteners/shorteners/bitly.py
pyshorteners/shorteners/chilpit.py
pyshorteners/shorteners/clckru.py
pyshorteners/shorteners/cuttly.py
pyshorteners/shorteners/dagd.py
pyshorteners/shorteners/gitio.py
pyshorteners/shorteners/isgd.py
pyshorteners/shorteners/nullpointer.py
pyshorteners/shorteners/osdb.py
pyshorteners/shorteners/owly.py
pyshorteners/shorteners/post.py
pyshorteners/shorteners/qpsru.py
pyshorteners/shorteners/shortcm.py
pyshorteners/shorteners/tinycc.py
pyshorteners/shorteners/tinyurl.py
theshorteners-0.0.1.dist-info/LICENSE
theshorteners-0.0.1.dist-info/METADATA
theshorteners-0.0.1.dist-info/WHEEL
theshorteners-0.0.1.dist-info/top_level.txt
theshorteners-0.0.1.dist-info/RECORD
